vcsp_guard/__init__.py
vcsp_guard/generate_stats.py
vcsp_guard/install_hooks.py
vcsp_guard/main.py
vcsp_guard/scan_project.py
vcsp_guard/.vibe/.clinerules
vcsp_guard/.vibe/.codiumai.toml
vcsp_guard/.vibe/.cursorrules
vcsp_guard/.vibe/AUDITORIA_IA.md
vcsp_guard/.vibe/GEMINI.md
vcsp_guard/.vibe/.github/copilot-instructions.md
vcsp_guard/.vibe/.github/dependabot.yml
vcsp_guard/.vibe/.github/workflows/dependabot-auto-merge.yml
vcsp_guard/.vibe/.github/workflows/dependabot-pr-tests.yml
vcsp_guard/.vibe/.github/workflows/publish_release.yml
vcsp_guard/.vibe/.github/workflows/security_scan.yml
vcsp_guard-1.0.3.8.dist-info/licenses/LICENSE
vcsp_guard-1.0.3.8.dist-info/METADATA
vcsp_guard-1.0.3.8.dist-info/WHEEL
vcsp_guard-1.0.3.8.dist-info/entry_points.txt
vcsp_guard-1.0.3.8.dist-info/top_level.txt
vcsp_guard-1.0.3.8.dist-info/RECORD
