Metadata-Version: 2.4
Name: vcsp-guard
Version: 1.0.3.8
Summary: Vibe Coding Security Protocol - Security & Quality Guardrails for AI Coding
Author-email: Giordano Alves <giordano.alves9@gmail.com>
License: MIT License
Keywords: security,ai,audit,code-quality,guardrails,static-analysis
Classifier: Programming Language :: Python :: 3
Classifier: Programming Language :: Python :: 3.10
Classifier: Programming Language :: Python :: 3.11
Classifier: Programming Language :: Python :: 3.12
Classifier: Operating System :: OS Independent
Classifier: Topic :: Security
Classifier: Topic :: Software Development :: Quality Assurance
Requires-Python: >=3.10
License-File: LICENSE
Requires-Dist: pip-audit>=2.6.0
Requires-Dist: ruff>=0.1.0
Requires-Dist: semgrep>=1.0.0; sys_platform != "win32"
Provides-Extra: stats
Requires-Dist: matplotlib>=3.7.0; extra == "stats"
Provides-Extra: dev
Requires-Dist: pytest; extra == "dev"
Requires-Dist: black; extra == "dev"
Requires-Dist: mypy; extra == "dev"
Requires-Dist: types-setuptools; extra == "dev"
Requires-Dist: tomli>=2.0.0; python_version < "3.11" and extra == "dev"
Dynamic: license-file
